package/__init__.py
package/entrypoint.py
package/models/__init__.py
package/models/module_functions.py
package/models/mymodel.py
python_console_package/__init__.py
python_console_package/entrypoint.py
python_console_package/models/__init__.py
python_console_package/models/module_functions.py
python_console_package/models/mymodel.py
python_console_package/models/someresource.txt
python_console_package-1.0.0.dist-info/LICENSE.txt
python_console_package-1.0.0.dist-info/METADATA
python_console_package-1.0.0.dist-info/WHEEL
python_console_package-1.0.0.dist-info/entry_points.txt
python_console_package-1.0.0.dist-info/top_level.txt
python_console_package-1.0.0.dist-info/RECORD
