Metadata-Version: 2.1
Name: python-console-package
Version: 1.0.0
Summary: A small template for building and distibuting python console applications
Home-page: https://github.com/MarkusPeitl/python-console-template
Author: Markus Peitl
Author-email: office@markuspeitl.com
License: UNKNOWN
Platform: UNKNOWN
Classifier: Programming Language :: Python :: 3
Classifier: Intended Audience :: Developers
Classifier: License :: OSI Approved :: Apache Software License
Classifier: Natural Language :: English
Classifier: Topic :: Software Development :: Documentation
Requires-Python: >=3
Requires-Dist: argparse
